{
  "path": "/projects/beckley-retreats",
  "sourceUrl": "https://www.haggard.design/projects/beckley-retreats",
  "title": "Beckley Retreats",
  "bodyClass": "",
  "ogImage": "/assets/social-image.png",
  "htmlFile": "projects/beckley-retreats.html",
  "lastMigrated": "2026-05-28T05:19:48.331Z",
  "description": "Beckley Retreats required a platform that could support a sensitive, high-consideration customer journey. The work helped translate the organization's scientific credibility and retreat experience into a digital system that feels calm, trustworthy, and operationally clear for a new category of psilocybin care."
}
